coinmarket_service/__init__.py
coinmarket_service/server.py
mseep_coinmarket_service-0.1.4.dist-info/licenses/LICENSE
mseep_coinmarket_service-0.1.4.dist-info/METADATA
mseep_coinmarket_service-0.1.4.dist-info/WHEEL
mseep_coinmarket_service-0.1.4.dist-info/entry_points.txt
mseep_coinmarket_service-0.1.4.dist-info/top_level.txt
mseep_coinmarket_service-0.1.4.dist-info/RECORD
