Metadata-Version: 2.4
Name: mseep-coinmarket-service
Version: 0.1.4
Summary: Coinmarket MCP Server
Author-email: mseep <support@skydeck.ai>
Requires-Python: >=3.12
License-File: LICENSE
Requires-Dist: mcp>=1.0.0
Requires-Dist: python-dotenv>=1.0.1
Requires-Dist: requests>=2.32.3
Requires-Dist: ruff>=0.8.1
Dynamic: license-file
